design.sv
`timescale 1ns / 1ps

module cache (
    input clk,
    input rst,
    input [7:0] address,
    input req_valid,
    input req_write,
    input [7:0] wdata,
    output reg [7:0] rdata,
    output reg hit,
    output reg ready
);

    reg [7:0] cache_data [0:3];
    reg [3:0] cache_valid;
    reg [1:0] cache_tags [0:3];

    reg mshr_valid [0:1];
    reg mshr_write [0:1];
    reg [7:0] mshr_addr [0:1];
    reg [7:0] mshr_data [0:1];
    reg [2:0] mshr_timer [0:1];

    integer i;
    reg allocated;

    wire [1:0] index = address[1:0];
    wire [1:0] tag   = address[3:2];

    always @(posedge clk or posedge rst) begin
        if (rst) begin
            cache_valid <= 0;
            hit <= 0;
            ready <= 1;
            rdata <= 0;
            for (i = 0; i < 2; i = i + 1) begin
                mshr_valid[i] <= 0;
                mshr_timer[i] <= 0;
            end
        end else begin
            hit <= 0;
            ready <= 1;

            if (req_valid) begin
                if (cache_valid[index] && cache_tags[index] == tag) begin
                    hit <= 1;
                    if (req_write)
                        cache_data[index] <= wdata;
                    else
                        rdata <= cache_data[index];
                end else begin
                    hit <= 0;
                    allocated = 0;
                    for (i = 0; i < 2; i = i + 1) begin
                        if (!mshr_valid[i] && !allocated) begin
                            mshr_valid[i] <= 1;
                            mshr_addr[i] <= address;
                            mshr_data[i] <= wdata;
                            mshr_write[i] <= req_write;
                            mshr_timer[i] <= 4;
                            ready <= 0;
                            allocated = 1;
                        end
                    end
                end
            end

            for (i = 0; i < 2; i = i + 1) begin
                if (mshr_valid[i]) begin
                    if (mshr_timer[i] > 0)
                        mshr_timer[i] <= mshr_timer[i] - 1;
                    else begin
                        cache_tags[mshr_addr[i][1:0]] <= mshr_addr[i][3:2];
                        cache_valid[mshr_addr[i][1:0]] <= 1;
                        cache_data[mshr_addr[i][1:0]] <= mshr_write[i] ? mshr_data[i] : 8'hAA;
                        mshr_valid[i] <= 0;
                    end
                end
            end
        end
    end

endmodule

testbench.sv
`timescale 1ns / 1ps

module testbench;

    reg clk;
    reg rst;
    reg [7:0] address;
    reg req_valid;
    reg req_write;
    reg [7:0] wdata;
    wire [7:0] rdata;
    wire hit;
    wire ready;

    cache uut (
        .clk(clk),
        .rst(rst),
        .address(address),
        .req_valid(req_valid),
        .req_write(req_write),
        .wdata(wdata),
        .rdata(rdata),
        .hit(hit),
        .ready(ready)
    );

    // Clock generation
    initial begin
        clk = 0;
        forever #5 clk = ~clk;
    end

    // Main test sequence
    initial begin
        $display("Time\tAddr\tHit\tReady\tRData");

        rst = 1; address = 0; req_valid = 0; req_write = 0; wdata = 0;
        #10 rst = 0;

        // Write to 0x01 with 0xDE
        #10 send_write(8'h01, 8'hDE);

        // Wait for MSHR to complete
        #50;

        // Read from 0x01 — should HIT and return 0xDE
        send_read(8'h01);

        #50;

        // ---- MSHR Full Test ----
        $display("\n--- Testing MSHR Full Condition ---");

        #10 send_read(8'h10); // MSHR #0
        #10 send_read(8'h20); // MSHR #1
        #10 send_read(8'h30); // Should NOT allocate — no MSHRs left

        #50 send_read(8'h20); // Should hit after MSHR #1 fills
        #10 send_read(8'h10); // Should hit after MSHR #0 fills

        #50;

        // ---- Corner Case: Back-to-back Write-Read before Fill ----
        $display("\n--- Back-to-Back Write-Then-Read (Before Fill) ---");

        #10 send_write(8'h02, 8'hBE); // MSHR gets triggered

        #10 send_read(8'h02);         // Should MISS

        #50 send_read(8'h02);         // Should HIT and return BE

        #50 $finish;
    end

    // Tasks
    task send_write(input [7:0] addr, input [7:0] data);
        begin
            address = addr;
            wdata = data;
            req_write = 1;
            req_valid = 1;
            #10;
            req_valid = 0;
        end
    endtask

    task send_read(input [7:0] addr);
        begin
            address = addr;
            req_write = 0;
            req_valid = 1;
            #10;
            req_valid = 0;
        end
    endtask

    // Monitoring
    always @(posedge clk) begin
        $display("%4t\t%2h\t%b\t%b\t%2h", $time, address, hit, ready, rdata);
    end

    // Dump waveform
    initial begin
        $dumpfile("dump.vcd");
        $dumpvars(0, testbench);
    end

endmodule

dump.vcd
$date
	Sun Jul 13 01:51:38 2025
$end
$version
	Icarus Verilog
$end
$timescale
	1ps
$end
$scope module testbench $end
$var wire 1 ! ready $end
$var wire 8 " rdata [7:0] $end
$var wire 1 # hit $end
$var reg 8 $ address [7:0] $end
$var reg 1 % clk $end
$var reg 1 & req_valid $end
$var reg 1 ' req_write $end
$var reg 1 ( rst $end
$var reg 8 ) wdata [7:0] $end
$scope module uut $end
$var wire 8 * address [7:0] $end
$var wire 1 % clk $end
$var wire 1 & req_valid $end
$var wire 1 ' req_write $end
$var wire 1 ( rst $end
$var wire 8 + wdata [7:0] $end
$var wire 2 , tag [1:0] $end
$var wire 2 - index [1:0] $end
$var reg 1 . allocated $end
$var reg 4 / cache_valid [3:0] $end
$var reg 1 # hit $end
$var reg 8 0 rdata [7:0] $end
$var reg 1 ! ready $end
$var integer 32 1 i [31:0] $end
$upscope $end
$scope task send_read $end
$var reg 8 2 addr [7:0] $end
$upscope $end
$scope task send_write $end
$var reg 8 3 addr [7:0] $end
$var reg 8 4 data [7:0] $end
$upscope $end
$upscope $end
$enddefinitions $end
$comment Show the parameter values. $end
$dumpall
$end
#0
$dumpvars
bx 4
bx 3
bx 2
b10 1
b0 0
b0 /
x.
b0 -
b0 ,
b0 +
b0 *
b0 )
1(
0'
0&
0%
b0 $
0#
b0 "
1!
$end
#5000
b10 1
1%
#10000
0%
0(
#15000
b10 1
1%
#20000
b1 -
0%
1&
1'
b11011110 )
b11011110 +
b1 $
b1 *
b11011110 4
b1 3
#25000
0!
b10 1
1.
1%
#30000
0%
0&
#35000
1!
b10 1
1%
#40000
0%
#45000
b10 1
1%
#50000
0%
#55000
b10 1
1%
#60000
0%
#65000
b10 1
1%
#70000
0%
#75000
b10 /
b10 1
1%
#80000
0%
1&
0'
b1 2
#85000
b11011110 "
b11011110 0
1#
b10 1
1%
#90000
0%
0&
#95000
0#
b10 1
1%
#100000
0%
#105000
b10 1
1%
#110000
0%
#115000
b10 1
1%
#120000
0%
#125000
b10 1
1%
#130000
0%
#135000
b10 1
1%
#140000
0%
#145000
b10 1
1%
#150000
b0 -
0%
1&
b10000 $
b10000 *
b10000 2
#155000
0!
b10 1
1.
1%
#160000
0%
0&
#165000
1!
b10 1
1%
#170000
0%
1&
b100000 $
b100000 *
b100000 2
#175000
0!
b10 1
1.
1%
#180000
0%
0&
#185000
1!
b10 1
1%
#190000
0%
1&
b110000 $
b110000 *
b110000 2
#195000
b10 1
0.
1%
#200000
0%
0&
#205000
b11 /
b10 1
1%
#210000
0%
#215000
b10 1
1%
#220000
0%
#225000
b10 1
1%
#230000
0%
#235000
b10 1
1%
#240000
0%
#245000
b10 1
1%
#250000
0%
1&
b100000 $
b100000 *
b100000 2
#255000
b10101010 "
b10101010 0
1#
b10 1
1%
#260000
0%
0&
#265000
0#
b10 1
1%
#270000
0%
1&
b10000 $
b10000 *
b10000 2
#275000
1#
b10 1
1%
#280000
0%
0&
#285000
0#
b10 1
1%
#290000
0%
#295000
b10 1
1%
#300000
0%
#305000
b10 1
1%
#310000
0%
#315000
b10 1
1%
#320000
0%
#325000
b10 1
1%
#330000
0%
#335000
b10 1
1%
#340000
b10 -
0%
1&
1'
b10111110 )
b10111110 +
b10 $
b10 *
b10111110 4
b10 3
#345000
0!
1.
b10 1
1%
#350000
0%
0&
#355000
1!
b10 1
1%
#360000
0%
1&
0'
b10 2
#365000
0!
b10 1
1.
1%
#370000
0%
0&
#375000
1!
b10 1
1%
#380000
0%
#385000
b10 1
1%
#390000
0%
#395000
b111 /
b10 1
1%
#400000
0%
#405000
b10 1
1%
#410000
0%
#415000
b10 1
1%
#420000
0%
1&
#425000
1#
b10 1
1%
#430000
0%
0&
#435000
0#
b10 1
1%
#440000
0%
#445000
b10 1
1%
#450000
0%
#455000
b10 1
1%
#460000
0%
#465000
b10 1
1%
#470000
0%
#475000
b10 1
1%
